{"errors":[],"warnings":[],"namedChunkGroups":{"app":{"chunks":[5,0,1],"assets":["webpack-runtime-c6673018cb9e03dbc91d.js","webpack-runtime-c6673018cb9e03dbc91d.js.map","commons.a96ca7369e8d4de9e112.css","commons-62ef5c1206db06296a14.js","commons-62ef5c1206db06296a14.js.map","app-5ade4e570610e20fcdd4.js","app-5ade4e570610e20fcdd4.js.map"],"children":{},"childAssets":{}},"component---src-pages-404-js":{"chunks":[0,2],"assets":["commons.a96ca7369e8d4de9e112.css","commons-62ef5c1206db06296a14.js","commons-62ef5c1206db06296a14.js.map","component---src-pages-404-js-da5d9412f70bf01c058c.js","component---src-pages-404-js-da5d9412f70bf01c058c.js.map"],"children":{},"childAssets":{}},"component---src-pages-index-js":{"chunks":[0,4,3],"assets":["commons.a96ca7369e8d4de9e112.css","commons-62ef5c1206db06296a14.js","commons-62ef5c1206db06296a14.js.map","styles.d6f014d089de406687e4.css","styles-215854a9608e5073fed2.js","styles-215854a9608e5073fed2.js.map","component---src-pages-index-js-e133d4cef47341de75a7.js","component---src-pages-index-js-e133d4cef47341de75a7.js.map"],"children":{},"childAssets":{}}},"assetsByChunkName":{"app":["webpack-runtime-c6673018cb9e03dbc91d.js","commons.a96ca7369e8d4de9e112.css","commons-62ef5c1206db06296a14.js","app-5ade4e570610e20fcdd4.js"],"component---src-pages-404-js":["commons.a96ca7369e8d4de9e112.css","commons-62ef5c1206db06296a14.js","component---src-pages-404-js-da5d9412f70bf01c058c.js"],"component---src-pages-index-js":["commons.a96ca7369e8d4de9e112.css","commons-62ef5c1206db06296a14.js","styles.d6f014d089de406687e4.css","styles-215854a9608e5073fed2.js","component---src-pages-index-js-e133d4cef47341de75a7.js"]}}